{
  "headers": {
    "content-type": "application/typescript; charset=utf-8",
    "x-amz-cf-pop": "HEL51-P2",
    "x-amz-replication-status": "FAILED",
    "content-length": "87",
    "via": "http/2 edgeproxy-h",
    "content-security-policy": "default-src 'none'; style-src 'unsafe-inline'; sandbox",
    "x-amz-cf-id": "bMtRieRhxqlg5R3p5MIs0LJkaN__4ypv1Afyy11p7515iRKY9B4mig==",
    "age": "10253006",
    "vary": "Accept-Encoding, Origin",
    "x-amz-version-id": "1U61dp3LgzWP6htoJWMi08aQDH5GXHFg",
    "date": "Tue, 27 Sep 2022 01:40:51 GMT",
    "etag": "\"fcedf961bc626fd76a0c85089f1afb10\"",
    "server": "deno/gcp-europe-north1",
    "last-modified": "Fri, 25 Mar 2022 13:32:50 GMT",
    "accept-ranges": "bytes",
    "access-control-allow-origin": "*",
    "x-cache": "Hit from cloudfront",
    "cache-control": "public, max-age=31536000, immutable"
  },
  "url": "https://deno.land/std@0.132.0/node/internal_binding/serdes.ts",
  "now": {
    "secs_since_epoch": 1674495856,
    "nanos_since_epoch": 406422975
  }
}