{
  "headers": {
    "access-control-allow-origin": "*",
    "age": "12170423",
    "content-length": "1354",
    "last-modified": "Fri, 25 Mar 2022 13:32:50 GMT",
    "vary": "Accept-Encoding, Origin",
    "x-amz-replication-status": "FAILED",
    "content-security-policy": "default-src 'none'; style-src 'unsafe-inline'; sandbox",
    "server": "deno/gcp-europe-north1",
    "content-type": "application/typescript; charset=utf-8",
    "x-amz-cf-pop": "HEL51-P2",
    "x-amz-cf-id": "RjRdC8xUuG_MR5aPsl_k4fXIou_eT95kXLaIKFU13D0O-IE1iT5rzQ==",
    "x-amz-version-id": "5lnI0UnRKbrG4EDqqjwu1dR9Wsu0dgzG",
    "via": "http/2 edgeproxy-h",
    "cache-control": "public, max-age=31536000, immutable",
    "x-cache": "Hit from cloudfront",
    "etag": "\"d2d58d0d3060da4f4da39060517bad59\"",
    "date": "Sun, 04 Sep 2022 21:03:52 GMT",
    "accept-ranges": "bytes"
  },
  "url": "https://deno.land/std@0.132.0/node/crypto.ts",
  "now": {
    "secs_since_epoch": 1674495854,
    "nanos_since_epoch": 779094259
  }
}