{
  "headers": {
    "accept-ranges": "bytes",
    "etag": "\"6fda6ccbf2319b0d5357b25214114e99\"",
    "content-security-policy": "default-src 'none'; style-src 'unsafe-inline'; sandbox",
    "date": "Thu, 15 Sep 2022 20:36:47 GMT",
    "x-cache": "Hit from cloudfront",
    "server": "deno/gcp-europe-north1",
    "via": "http/2 edgeproxy-h",
    "access-control-allow-origin": "*",
    "cache-control": "public, max-age=31536000, immutable",
    "vary": "Accept-Encoding, Origin",
    "last-modified": "Fri, 25 Mar 2022 13:32:47 GMT",
    "x-amz-cf-id": "XWM3UJEXDQOsjdd_7OAgdBy7Ur2uGtTBw3CN6tqmka5wlUwtr7AJGA==",
    "x-amz-cf-pop": "HEL51-P2",
    "x-amz-version-id": "oIzznjBTsMkDWbxNH0TfnMNz6FDRtQKC",
    "x-amz-replication-status": "FAILED",
    "age": "12417047",
    "content-length": "1475",
    "content-type": "application/typescript; charset=utf-8"
  },
  "url": "https://deno.land/std@0.132.0/encoding/base64url.ts",
  "now": {
    "secs_since_epoch": 1675691254,
    "nanos_since_epoch": 202538992
  }
}