{
  "headers": {
    "vary": "Accept-Encoding, Origin",
    "x-amz-cf-id": "wf03coFSMkhmmP1T0Ogxr8545Os2PLFvd_ucQdhLC4WQDmgaM_lmQw==",
    "x-amz-replication-status": "FAILED",
    "cache-control": "public, max-age=31536000, immutable",
    "age": "10598997",
    "etag": "\"39fd7d662a5773a403746ffeb1166c7c\"",
    "date": "Fri, 23 Sep 2022 07:00:55 GMT",
    "x-amz-version-id": "G912c6a_.SO2R_ba8NapCmGd_AzGdOal",
    "access-control-allow-origin": "*",
    "last-modified": "Fri, 25 Mar 2022 13:32:50 GMT",
    "x-cache": "Hit from cloudfront",
    "content-type": "application/typescript; charset=utf-8",
    "server": "deno/gcp-europe-north1",
    "via": "http/2 edgeproxy-h",
    "x-amz-cf-pop": "HEL51-P2",
    "content-security-policy": "default-src 'none'; style-src 'unsafe-inline'; sandbox",
    "content-length": "70118",
    "accept-ranges": "bytes"
  },
  "url": "https://deno.land/std@0.132.0/node/internal/errors.ts",
  "now": {
    "secs_since_epoch": 1674515452,
    "nanos_since_epoch": 722123725
  }
}