{
  "headers": {
    "x-cache": "Hit from cloudfront",
    "cache-control": "public, max-age=31536000, immutable",
    "content-security-policy": "default-src 'none'; style-src 'unsafe-inline'; sandbox",
    "etag": "W/\"8b36c43088485ca65c5fe5430fa16482\"",
    "vary": "Accept-Encoding, Origin",
    "x-amz-cf-pop": "HEL51-P2",
    "x-amz-replication-status": "FAILED",
    "content-type": "application/javascript",
    "server": "deno/gcp-europe-north1",
    "via": "http/2 edgeproxy-h",
    "x-amz-version-id": "bWdhsv72FJwkoCrNOIiBoRJdsMBWLDeg",
    "x-amz-cf-id": "-cYJrQFzCIud3eY_9gMs2P38OcduSzEh5VoYnJ4zQvrjpBEGR6f1Vw==",
    "last-modified": "Fri, 25 Mar 2022 13:32:48 GMT",
    "access-control-allow-origin": "*",
    "age": "12434754",
    "date": "Fri, 02 Sep 2022 01:05:00 GMT"
  },
  "url": "https://deno.land/std@0.132.0/node/_crypto/crypto_browserify/browserify_aes/modes/ctr.js",
  "now": {
    "secs_since_epoch": 1674515453,
    "nanos_since_epoch": 320525138
  }
}