{
  "headers": {
    "content-security-policy": "default-src 'none'; style-src 'unsafe-inline'; sandbox",
    "date": "Tue, 06 Sep 2022 08:48:14 GMT",
    "vary": "Accept-Encoding, Origin",
    "content-length": "322",
    "accept-ranges": "bytes",
    "x-cache": "Hit from cloudfront",
    "x-amz-replication-status": "FAILED",
    "x-amz-version-id": "PxAxDg8KE06Dh7aGdSJGfWIzYzDyPEMv",
    "x-amz-cf-id": "Nb7haOakavBEAdu7_DODPqVKtdRpZVRDH1cyQPCiBPBjX0noZDvDAQ==",
    "x-amz-cf-pop": "HEL51-P2",
    "content-type": "application/typescript; charset=utf-8",
    "etag": "\"4bcd3605cef1881f3181957fdeb12bab\"",
    "access-control-allow-origin": "*",
    "last-modified": "Fri, 25 Mar 2022 13:32:50 GMT",
    "via": "http/2 edgeproxy-h",
    "cache-control": "public, max-age=31536000, immutable",
    "age": "12044037",
    "server": "deno/gcp-europe-north1"
  },
  "url": "https://deno.land/std@0.132.0/node/internal/error_codes.ts",
  "now": {
    "secs_since_epoch": 1674498130,
    "nanos_since_epoch": 441585312
  }
}